circuit/__init__.py
circuit/_twisted.py
circuit/breaker.py
python_circuit-0.1.9.dist-info/DESCRIPTION.rst
python_circuit-0.1.9.dist-info/METADATA
python_circuit-0.1.9.dist-info/RECORD
python_circuit-0.1.9.dist-info/WHEEL
python_circuit-0.1.9.dist-info/metadata.json
python_circuit-0.1.9.dist-info/top_level.txt
