Metadata-Version: 2.0
Name: python-circuit
Version: 0.1.9
Summary: Simple implementation of the Circuit Breaker pattern
Home-page: https://github.com/edgeware/python-circuit
Author: Edgeware
Author-email: info@edgeware.tv
License: Apache v2.0 License
Platform: UNKNOWN
